algorythm/__init__.py
algorythm/__main__.py
algorythm/backend.py
algorythm/bars.py
algorythm/collect_media_info.py
algorythm/graphics.py
algorythm/menu.py
algorythm/pygame_objects.py
algorythm/settings.py
algorythm/spotipy_implementation.py
algorythm-1.0.1.dist-info/LICENSE
algorythm-1.0.1.dist-info/METADATA
algorythm-1.0.1.dist-info/WHEEL
algorythm-1.0.1.dist-info/top_level.txt
algorythm-1.0.1.dist-info/RECORD
