Metadata-Version: 2.1
Name: algorythm
Version: 1.0.1
Summary: A python audio visualizer
Home-page: https://github.com/cburrows1/AlgoRythm
Author: Snake Charmers
Author-email: laurence.mullen@ufl.edu
License: UNKNOWN
Project-URL: Bug Tracker, https://github.com/cburrows1/AlgoRythm/issues
Platform: UNKNOWN
Classifier: Programming Language :: Python :: 3
Classifier: License :: OSI Approved :: GNU General Public License v3 (GPLv3)
Classifier: Operating System :: Microsoft :: Windows :: Windows 10
Requires-Python: >=3.8
License-File: LICENSE
Requires-Dist: pyaudio
Requires-Dist: numpy
Requires-Dist: scipy
Requires-Dist: pygame
Requires-Dist: pywin32
Requires-Dist: winrt
Requires-Dist: requests
Requires-Dist: pillow
Requires-Dist: spotipy
